lens/__init__.py
lens/collect_data.py
lens/run_model.py
lens/run_speck.py
lens/train_model.py
lens/src/__init__.py
lens/src/blitnet.py
lens/src/dataset.py
lens/src/demo.py
lens/src/loggers.py
lens/src/match.py
lens/src/metrics.py
lens/src/sad.py
lens/src/speck2f.py
lens/tools/__init__.py
lens/tools/checker.py
lens/tools/create_GTtol.py
lens/tools/create_data_csv.py
lens/tools/dvstools.py
lens/tools/manual_eventframe_generator.py
lens/tools/matching_plots.py
lens/tools/plot_results.py
lens/tools/process_dvs.py
lens/tools/read_gps.py
lens/tools/rename_images.py
lens_vpr-0.1.5.data/scripts/main.py
lens_vpr-0.1.5.dist-info/LICENSE
lens_vpr-0.1.5.dist-info/METADATA
lens_vpr-0.1.5.dist-info/WHEEL
lens_vpr-0.1.5.dist-info/top_level.txt
lens_vpr-0.1.5.dist-info/RECORD
