Metadata-Version: 2.1
Name: lens-vpr
Version: 0.1.5
Summary: LENS: Locational Encoding with Neuromorphic Systems
Home-page: https://github.com/AdamDHines/LENS
Author: Adam D Hines, Michael Milford and Tobias Fischer
Author-email: adam.hines@qut.edu.au
License: MIT
Keywords: robotics,visual-place-recognition,neuromorphic-computing,spiking-neural-network,dynamic-vision-sensors
Classifier: Development Status :: 4 - Beta
Classifier: Intended Audience :: Developers
Classifier: License :: OSI Approved :: MIT License
Classifier: Programming Language :: Python :: 3.6
Classifier: Programming Language :: Python :: 3.7
Classifier: Programming Language :: Python :: 3.8
Classifier: Programming Language :: Python :: 3.9
Classifier: Programming Language :: Python :: 3.10
Classifier: Programming Language :: Python :: 3.11
Requires-Python: >=3.6, !=3.12.*
License-File: LICENSE
Requires-Dist: torch>=2.1.1
Requires-Dist: torchvision>=0.16.1
Requires-Dist: numpy>=1.26.2
Requires-Dist: pandas>=2.1.1
Requires-Dist: tqdm>=4.65.0
Requires-Dist: prettytable>=3.5.0
Requires-Dist: scikit-learn>=1.2.2
Requires-Dist: sinabs>=3.0.1
Requires-Dist: h5py>=3.10.0
Requires-Dist: imageio>=2.34.1
Requires-Dist: matplotlib>=3.8.2
Requires-Dist: pynmea2>=1.19.0
Requires-Dist: scipy>=1.11.4
Requires-Dist: wandb>=0.16.2
